AUTHORS.rst
CONTRIBUTING.rst
HISTORY.rst
MANIFEST.in
README.rst
setup.cfg
setup.py
docs/Makefile
docs/authors.rst
docs/conf.py
docs/contributing.rst
docs/history.rst
docs/index.rst
docs/installation.rst
docs/make.bat
docs/readme.rst
docs/usage.rst
sphinx_numfig/__init__.py
sphinx_numfig/numfig.py
sphinx_numfig/numimg.py
sphinx_numfig/sphinx-numfig.py
sphinx_numfig.egg-info/PKG-INFO
sphinx_numfig.egg-info/SOURCES.txt
sphinx_numfig.egg-info/dependency_links.txt
sphinx_numfig.egg-info/not-zip-safe
sphinx_numfig.egg-info/top_level.txt
tests/.test_sphinx_numfig.py.un~
tests/__init__.py
tests/test_sphinx_numfig.py